pystalkd/Beanstalkd.py
pystalkd/Job.py
pystalkd/__init__.py
pystalkd-1.3.0.dist-info/LICENSE
pystalkd-1.3.0.dist-info/METADATA
pystalkd-1.3.0.dist-info/WHEEL
pystalkd-1.3.0.dist-info/top_level.txt
pystalkd-1.3.0.dist-info/RECORD
