Metadata-Version: 2.1
Name: pystalkd
Version: 1.3.0
Summary: Beanstalkd bindings for python3
Home-page: https://github.com/menezes-/pystalkd
Author: Gabriel
Author-email: gabrielmenezesvi@gmail.com
License: MIT
Download-URL: https://github.com/menezes-/pystalkd/archive/v1.3.0.zip
Keywords: beanstalkd,python3,bindings
Platform: UNKNOWN
Provides-Extra: yaml
Requires-Dist: PyYAML ; extra == 'yaml'
